flouter/__init__.py
flouter/helpers.py
flouter/logging.py
flouter/router.py
flouter-0.0.6.dev0.dist-info/LICENSE.rst
flouter-0.0.6.dev0.dist-info/METADATA
flouter-0.0.6.dev0.dist-info/WHEEL
flouter-0.0.6.dev0.dist-info/top_level.txt
flouter-0.0.6.dev0.dist-info/RECORD
